log10/__init__.py
log10/__main__.py
log10/_httpx_utils.py
log10/agents/camel.py
log10/agents/scrape_summarizer.py
log10/anthropic.py
log10/bigquery.py
log10/cli/autofeedback.py
log10/cli/autoprompt.py
log10/cli/cli_commands.py
log10/cli/completions.py
log10/cli/feedback.py
log10/cli/feedback_task.py
log10/cli_utils.py
log10/completions/__init__.py
log10/completions/completions.py
log10/evals.py
log10/feedback/_summary_feedback_utils.py
log10/feedback/autofeedback.py
log10/feedback/feedback.py
log10/feedback/feedback_task.py
log10/langchain.py
log10/litellm.py
log10/llm.py
log10/load.py
log10/mosaicml.py
log10/openai.py
log10/prompt_analyzer.py
log10/pytest_log10_managed_evaluation/README.md
log10/pytest_log10_managed_evaluation/__init__.py
log10/pytest_log10_managed_evaluation/plugin.py
log10/pytest_log10_managed_evaluation/serialize.py
log10/pytest_log10_managed_evaluation/utils.py
log10/schemas/bigquery.json
log10/together.py
log10/tools.py
log10/utils.py
log10_io-0.16.1.dist-info/LICENSE
log10_io-0.16.1.dist-info/METADATA
log10_io-0.16.1.dist-info/WHEEL
log10_io-0.16.1.dist-info/entry_points.txt
log10_io-0.16.1.dist-info/RECORD
