Metadata-Version: 2.3
Name: log10-io
Version: 0.16.1
Summary: Unified LLM data management
License: MIT
Author: log10 team
Requires-Python: >=3.10,<4.0
Classifier: License :: OSI Approved :: MIT License
Classifier: Operating System :: OS Independent
Classifier: Programming Language :: Python :: 3
Classifier: Programming Language :: Python :: 3.10
Classifier: Programming Language :: Python :: 3.11
Classifier: Programming Language :: Python :: 3.12
Classifier: Programming Language :: Python :: 3.13
Provides-Extra: autofeedback-icl
Provides-Extra: cli
Provides-Extra: gemini
Provides-Extra: google-generativeai
Provides-Extra: langchain
Provides-Extra: litellm
Provides-Extra: mistralai
Provides-Extra: mosaicml
Provides-Extra: together
Requires-Dist: aiohttp (>=3.11.10)
Requires-Dist: anthropic (<1)
Requires-Dist: anyio (>=4.4.0)
Requires-Dist: backoff (>=2.2.1,<3.0.0)
Requires-Dist: certifi (>=2024.7.4)
Requires-Dist: click (>=8.1.7,<9.0.0) ; extra == "cli"
Requires-Dist: cryptography (>=43.0.1)
Requires-Dist: google-cloud-aiplatform (>=1.44.0) ; extra == "gemini"
Requires-Dist: google-cloud-bigquery (>=3.11.4,<4.0.0)
Requires-Dist: google-generativeai (>=0.6.0,<0.7.0) ; extra == "google-generativeai"
Requires-Dist: jinja2 (>=3.1.5)
Requires-Dist: langchain (>=0.2.10,<0.3.0) ; extra == "langchain"
Requires-Dist: langchain-community (>=0.2.19,<0.3.0) ; extra == "langchain"
Requires-Dist: litellm (>=1.49.6) ; extra == "litellm"
Requires-Dist: magentic (==0.32.0) ; extra == "autofeedback-icl"
Requires-Dist: mistralai (>=0.1.5,<0.2.0) ; extra == "mistralai"
Requires-Dist: mosaicml-cli (>=0.5.30,<0.6.0) ; extra == "mosaicml"
Requires-Dist: openai (<2)
Requires-Dist: pandas (>=2) ; extra == "cli"
Requires-Dist: pytest (>=8.0.0)
Requires-Dist: pytest-metadata (>=1.0.0)
Requires-Dist: python-dotenv (>=1.0.0,<2.0.0)
Requires-Dist: requests (>=2.32.2,<3.0.0)
Requires-Dist: rich (>=13.7.1,<14.0.0) ; extra == "cli"
Requires-Dist: scikit-learn (>=1.5.0)
Requires-Dist: tabulate (>=0.9.0,<0.10.0) ; extra == "cli"
Requires-Dist: together (>=1.0.1,<2.0.0) ; extra == "together"
Requires-Dist: tqdm (>=4.66.3)
Requires-Dist: urllib3 (>=2.2.2)
Requires-Dist: zipp (>=3.19.1)
Project-URL: Bug Tracker, https://github.com/log10-io/log10/issues
Project-URL: Homepage, https://github.com/log10-io/log10
